automate_code/__init__.py
automate_code/management/__init__.py
automate_code/management/commands/__init__.py
automate_code/management/commands/code_generator.py
automate_code-0.1.0.dist-info/LICENSE
automate_code-0.1.0.dist-info/METADATA
automate_code-0.1.0.dist-info/WHEEL
automate_code-0.1.0.dist-info/entry_points.txt
automate_code-0.1.0.dist-info/top_level.txt
automate_code-0.1.0.dist-info/RECORD
